[
  {
    "_id": "5d810b50aae44ad1642651f2",
    "index": 1,
    "guid": "6573d7a0-6f70-4866-97c6-b85c881bc442",
    "isActive": false,
    "balance": "$2,414.54",
    "picture": "http://placehold.it/32x32",
    "age": 35,
    "eyeColor": "brown",
    "name": "Stephenson Foley",
    "gender": "male",
    "company": "ZOUNDS",
    "email": "stephensonfoley@zounds.com",
    "phone": "+1 (823) 459-3602",
    "address": "327 Wolf Place, Corinne, Alaska, 3097",
    "about": "Tempor labore ad nisi dolor anim id excepteur id exercitation laboris non culpa pariatur ullamco. Enim Lorem sit et dolore voluptate. Magna sunt velit cillum id do in nostrud tempor veniam adipisicing esse.\r\n",
    "registered": "2019-06-07T02:26:36 -06:-30",
    "latitude": -49.774364,
    "longitude": 72.541629,
    "tags": [
      "ullamco",
      "officia",
      "enim",
      "reprehenderit",
      "consectetur",
      "laboris",
      "in"
    ],
    "friends": [
      {
        "id": 0,
        "name": "Wendy Juarez"
      },
      {
        "id": 1,
        "name": "Miller Holland"
      },
      {
        "id": 2,
        "name": "Barbra Jarvis"
      }
    ],
    "greeting": "Hello, Stephenson Foley! You have 10 unread messages.",
    "favoriteFruit": "apple"
  },
  {
    "_id": "5d810b503132d6e3b67eb990",
    "index": 2,
    "guid": "f511c834-5379-487a-a2e7-4b1120f99a65",
    "isActive": true,
    "balance": "$3,032.90",
    "picture": "http://placehold.it/32x32",
    "age": 34,
    "eyeColor": "blue",
    "name": "Valeria Harmon",
    "gender": "female",
    "company": "FISHLAND",
    "email": "valeriaharmon@fishland.com",
    "phone": "+1 (926) 513-2263",
    "address": "447 Eldert Street, Lumberton, North Dakota, 4464",
    "about": "Nulla commodo minim voluptate est consectetur nisi consectetur do excepteur commodo fugiat sunt labore exercitation. Proident nostrud sint in irure aliqua anim culpa pariatur in laborum id. Dolore incididunt nisi adipisicing commodo non anim. Minim ex irure non velit deserunt tempor minim sit elit amet enim cupidatat laborum. Sint tempor amet enim proident. Fugiat consectetur fugiat et id esse labore dolor est non excepteur. Irure excepteur Lorem nisi ullamco sint est occaecat nostrud officia amet ullamco aute anim.\r\n",
    "registered": "2015-11-14T07:15:16 -06:-30",
    "latitude": 46.138941,
    "longitude": 96.410966,
    "tags": [
      "cillum",
      "nisi",
      "et",
      "tempor",
      "ullamco",
      "nulla",
      "aliquip"
    ],
    "friends": [
      {
        "id": 0,
        "name": "Peterson Noel"
      },
      {
        "id": 1,
        "name": "Betty Benton"
      },
      {
        "id": 2,
        "name": "Claire Baker"
      }
    ],
    "greeting": "Hello, Valeria Harmon! You have 9 unread messages.",
    "favoriteFruit": "apple"
  },
  {
    "_id": "5d810b50900745d96289d5c5",
    "index": 3,
    "guid": "f74fe157-5e0b-46ca-a725-722d58928548",
    "isActive": true,
    "balance": "$1,651.40",
    "picture": "http://placehold.it/32x32",
    "age": 21,
    "eyeColor": "green",
    "name": "Cain Phillips",
    "gender": "male",
    "company": "NUTRALAB",
    "email": "cainphillips@nutralab.com",
    "phone": "+1 (867) 563-3739",
    "address": "356 Fleet Place, Goodville, Illinois, 188",
    "about": "Laboris magna qui sint id duis. Incididunt cupidatat ipsum cupidatat elit minim aliquip deserunt cillum aute proident ipsum. Aute sit veniam nisi ullamco irure occaecat non labore sit incididunt quis ullamco adipisicing Lorem.\r\n",
    "registered": "2018-01-08T09:33:53 -06:-30",
    "latitude": -74.028643,
    "longitude": 140.10801,
    "tags": [
      "ut",
      "officia",
      "occaecat",
      "ex",
      "exercitation",
      "veniam",
      "officia"
    ],
    "friends": [
      {
        "id": 0,
        "name": "Freda Mason"
      },
      {
        "id": 1,
        "name": "Guy Morales"
      },
      {
        "id": 2,
        "name": "Althea Hays"
      }
    ],
    "greeting": "Hello, Cain Phillips! You have 7 unread messages.",
    "favoriteFruit": "apple"
  },
  {
    "_id": "5d810b504479d138d7938364",
    "index": 4,
    "guid": "14cb1a8a-2f82-42a9-8421-7869fea5e9f2",
    "isActive": true,
    "balance": "$2,290.19",
    "picture": "http://placehold.it/32x32",
    "age": 20,
    "eyeColor": "blue",
    "name": "Meyers Hodges",
    "gender": "male",
    "company": "ECLIPTO",
    "email": "meyershodges@eclipto.com",
    "phone": "+1 (885) 558-2560",
    "address": "872 Rutland Road, Trexlertown, Pennsylvania, 6542",
    "about": "Anim elit voluptate enim ad laboris magna consequat cillum proident pariatur. Voluptate excepteur exercitation sunt cillum enim incididunt consectetur. Dolor voluptate do cupidatat proident cupidatat cillum adipisicing labore minim ut commodo labore fugiat non. Nostrud occaecat ipsum et qui est esse ipsum ex amet proident deserunt incididunt.\r\n",
    "registered": "2014-05-10T03:49:38 -06:-30",
    "latitude": 6.21706,
    "longitude": -21.016204,
    "tags": [
      "enim",
      "laborum",
      "incididunt",
      "officia",
      "veniam",
      "reprehenderit",
      "labore"
    ],
    "friends": [
      {
        "id": 0,
        "name": "Elliott Munoz"
      },
      {
        "id": 1,
        "name": "Lane Nelson"
      },
      {
        "id": 2,
        "name": "Effie Rodgers"
      }
    ],
    "greeting": "Hello, Meyers Hodges! You have 9 unread messages.",
    "favoriteFruit": "banana"
  },
  {
    "_id": "5d810b50c17114345280fc82",
    "index": 5,
    "guid": "f31c4b53-9aaa-4f86-a4b4-6465e6903e2b",
    "isActive": false,
    "balance": "$3,980.47",
    "picture": "http://placehold.it/32x32",
    "age": 23,
    "eyeColor": "green",
    "name": "Nola Brown",
    "gender": "female",
    "company": "ANACHO",
    "email": "nolabrown@anacho.com",
    "phone": "+1 (962) 529-2135",
    "address": "748 Guider Avenue, Bynum, Texas, 4266",
    "about": "Consequat dolor id duis ut duis reprehenderit aliquip cillum laborum. Ut anim anim deserunt proident quis excepteur tempor reprehenderit aute. Eu reprehenderit voluptate eu Lorem tempor. Irure quis nostrud ea occaecat nisi ad mollit laboris ad reprehenderit dolor.\r\n",
    "registered": "2014-10-28T08:51:36 -06:-30",
    "latitude": 36.220676,
    "longitude": 57.165137,
    "tags": [
      "occaecat",
      "cillum",
      "nulla",
      "id",
      "laborum",
      "fugiat",
      "tempor"
    ],
    "friends": [
      {
        "id": 0,
        "name": "Alyce Wong"
      },
      {
        "id": 1,
        "name": "Browning Delgado"
      },
      {
        "id": 2,
        "name": "Chris Davis"
      }
    ],
    "greeting": "Hello, Nola Brown! You have 4 unread messages.",
    "favoriteFruit": "strawberry"
  },
  {
    "_id": "5d810b51590418cf1ca8cd57",
    "index": 6,
    "guid": "7a55ab77-a0e9-4e53-9ae7-0c15d8b7e77f",
    "isActive": true,
    "balance": "$1,482.78",
    "picture": "http://placehold.it/32x32",
    "age": 34,
    "eyeColor": "brown",
    "name": "Sawyer Oneil",
    "gender": "male",
    "company": "IMAGINART",
    "email": "sawyeroneil@imaginart.com",
    "phone": "+1 (801) 511-3676",
    "address": "133 Kosciusko Street, Salvo, Colorado, 285",
    "about": "Aliqua eiusmod qui in do non cupidatat. Laborum et laboris dolore sit tempor et. Eiusmod amet in cillum elit aute exercitation ut. Mollit ullamco est nulla eiusmod incididunt laboris est nisi amet deserunt. Enim aliqua exercitation aliquip tempor nisi enim. Laborum excepteur irure mollit tempor ea ea cupidatat ex pariatur duis et irure.\r\n",
    "registered": "2016-10-21T12:06:07 -06:-30",
    "latitude": -43.147288,
    "longitude": -3.314599,
    "tags": [
      "consequat",
      "aliquip",
      "ipsum",
      "non",
      "magna",
      "excepteur",
      "excepteur"
    ],
    "friends": [
      {
        "id": 0,
        "name": "Megan Flynn"
      },
      {
        "id": 1,
        "name": "Madelyn Ruiz"
      },
      {
        "id": 2,
        "name": "Eliza Burke"
      }
    ],
    "greeting": "Hello, Sawyer Oneil! You have 7 unread messages.",
    "favoriteFruit": "apple"
  },
  {
    "_id": "5d810b51da4464e1b055d39f",
    "index": 7,
    "guid": "0e598183-d613-4e14-95d5-2262861b0e13",
    "isActive": true,
    "balance": "$1,311.56",
    "picture": "http://placehold.it/32x32",
    "age": 39,
    "eyeColor": "green",
    "name": "Francine Herring",
    "gender": "female",
    "company": "ENDIPINE",
    "email": "francineherring@endipine.com",
    "phone": "+1 (858) 481-3441",
    "address": "668 Rockaway Parkway, Urbana, Kansas, 1976",
    "about": "Eu culpa labore adipisicing mollit veniam elit sunt dolor. Pariatur ex exercitation nulla tempor do in proident. Aliquip anim ipsum exercitation dolore nostrud proident.\r\n",
    "registered": "2016-12-25T12:31:59 -06:-30",
    "latitude": 13.714839,
    "longitude": -107.438602,
    "tags": [
      "do",
      "ullamco",
      "labore",
      "aute",
      "esse",
      "magna",
      "ad"
    ],
    "friends": [
      {
        "id": 0,
        "name": "Franco Callahan"
      },
      {
        "id": 1,
        "name": "Jessica Cash"
      },
      {
        "id": 2,
        "name": "Araceli Hester"
      }
    ],
    "greeting": "Hello, Francine Herring! You have 10 unread messages.",
    "favoriteFruit": "strawberry"
  },
  {
    "_id": "5d810b51c13e74d15dc46405",
    "index": 8,
    "guid": "0f41e244-b3fd-46a4-a9fb-b4a16021a9f3",
    "isActive": false,
    "balance": "$1,447.90",
    "picture": "http://placehold.it/32x32",
    "age": 23,
    "eyeColor": "green",
    "name": "Boone Tillman",
    "gender": "male",
    "company": "DARWINIUM",
    "email": "boonetillman@darwinium.com",
    "phone": "+1 (906) 508-2122",
    "address": "740 Nostrand Avenue, Coalmont, Idaho, 4054",
    "about": "Consequat sint aliqua pariatur minim culpa. Consectetur nostrud velit tempor sunt esse ex magna enim exercitation fugiat aute amet. Sunt consectetur incididunt consectetur enim deserunt dolor. Laboris labore id est laboris. Reprehenderit et magna ea et laborum irure commodo nulla in ullamco proident aliqua irure. Ipsum officia proident consequat ipsum enim incididunt excepteur nulla velit. Non qui ex esse aliquip.\r\n",
    "registered": "2017-10-17T04:13:55 -06:-30",
    "latitude": -47.943637,
    "longitude": 61.109357,
    "tags": [
      "aliqua",
      "commodo",
      "anim",
      "excepteur",
      "mollit",
      "quis",
      "tempor"
    ],
    "friends": [
      {
        "id": 0,
        "name": "Daisy Collins"
      },
      {
        "id": 1,
        "name": "Hubbard Lawson"
      },
      {
        "id": 2,
        "name": "Maude Alexander"
      }
    ],
    "greeting": "Hello, Boone Tillman! You have 8 unread messages.",
    "favoriteFruit": "apple"
  },
  {
    "_id": "5d810b512aee94e2a16a604e",
    "index": 9,
    "guid": "4bda1fe6-e11e-4225-aa28-e44f9dada4e6",
    "isActive": true,
    "balance": "$1,613.46",
    "picture": "http://placehold.it/32x32",
    "age": 22,
    "eyeColor": "green",
    "name": "Haynes Villarreal",
    "gender": "male",
    "company": "SONGLINES",
    "email": "haynesvillarreal@songlines.com",
    "phone": "+1 (903) 400-2121",
    "address": "404 Howard Place, Harmon, Alabama, 7333",
    "about": "Labore aliqua laborum laborum voluptate. Tempor officia ad cillum voluptate anim dolor exercitation. Eiusmod minim cillum deserunt amet esse sint quis consequat duis occaecat amet exercitation ullamco cillum. Amet ad consequat sit et dolore id tempor est labore laboris enim sit aliqua consectetur. Cupidatat irure magna anim tempor excepteur exercitation deserunt sunt eu sint dolor. Dolor magna aliquip eiusmod ad.\r\n",
    "registered": "2015-07-27T03:48:15 -06:-30",
    "latitude": 86.053886,
    "longitude": -154.884368,
    "tags": [
      "velit",
      "officia",
      "duis",
      "id",
      "anim",
      "sit",
      "voluptate"
    ],
    "friends": [
      {
        "id": 0,
        "name": "Aurora Wagner"
      },
      {
        "id": 1,
        "name": "Isabelle Bass"
      },
      {
        "id": 2,
        "name": "Melva Leach"
      }
    ],
    "greeting": "Hello, Haynes Villarreal! You have 9 unread messages.",
    "favoriteFruit": "banana"
  },
  {
    "_id": "5d810b5135456e1c6592f051",
    "index": 10,
    "guid": "e7111aa5-bd92-4099-9c19-36f3a1bbeb2d",
    "isActive": false,
    "balance": "$1,580.09",
    "picture": "http://placehold.it/32x32",
    "age": 40,
    "eyeColor": "brown",
    "name": "Decker William",
    "gender": "male",
    "company": "SARASONIC",
    "email": "deckerwilliam@sarasonic.com",
    "phone": "+1 (833) 573-3314",
    "address": "921 Stone Avenue, Neibert, Indiana, 9655",
    "about": "Aliqua tempor do dolor tempor. Commodo amet nisi cupidatat ex. Ipsum pariatur nisi fugiat ipsum sit tempor magna et adipisicing cillum. Velit culpa reprehenderit anim ut laborum labore ad irure mollit proident reprehenderit nisi cillum. Labore ex culpa nostrud pariatur eu quis Lorem labore officia occaecat consectetur aute.\r\n",
    "registered": "2016-03-24T03:24:13 -06:-30",
    "latitude": -88.687919,
    "longitude": -141.251717,
    "tags": [
      "officia",
      "duis",
      "commodo",
      "laborum",
      "adipisicing",
      "cillum",
      "sit"
    ],
    "friends": [
      {
        "id": 0,
        "name": "Burris Day"
      },
      {
        "id": 1,
        "name": "Gray Cochran"
      },
      {
        "id": 2,
        "name": "Hilda Leon"
      }
    ],
    "greeting": "Hello, Decker William! You have 10 unread messages.",
    "favoriteFruit": "apple"
  },
  {
    "_id": "5d810b5168ad120060eb8151",
    "index": 11,
    "guid": "ddc491ea-0ba0-44d9-a20c-e968d6d6df54",
    "isActive": true,
    "balance": "$2,018.52",
    "picture": "http://placehold.it/32x32",
    "age": 26,
    "eyeColor": "brown",
    "name": "Ellis Vinson",
    "gender": "male",
    "company": "OULU",
    "email": "ellisvinson@oulu.com",
    "phone": "+1 (966) 453-3839",
    "address": "232 Rock Street, Derwood, American Samoa, 3596",
    "about": "Aliqua excepteur qui ea deserunt. Quis fugiat ad labore sit quis aliqua amet occaecat laborum nostrud cillum tempor sint. In Lorem officia nostrud adipisicing velit aute reprehenderit voluptate ea elit do id ea. Amet voluptate ut id consequat in et.\r\n",
    "registered": "2018-06-15T01:49:27 -06:-30",
    "latitude": -23.585609,
    "longitude": -148.407375,
    "tags": [
      "quis",
      "in",
      "dolore",
      "fugiat",
      "esse",
      "fugiat",
      "ex"
    ],
    "friends": [
      {
        "id": 0,
        "name": "Anita Greer"
      },
      {
        "id": 1,
        "name": "Kelly Pickett"
      },
      {
        "id": 2,
        "name": "Dickson Miranda"
      }
    ],
    "greeting": "Hello, Ellis Vinson! You have 2 unread messages.",
    "favoriteFruit": "apple"
  },
  {
    "_id": "5d810b518d84daa566f0e7fe",
    "index": 12,
    "guid": "8ec0b37a-5649-4861-b808-1672b66775e5",
    "isActive": true,
    "balance": "$1,461.22",
    "picture": "http://placehold.it/32x32",
    "age": 38,
    "eyeColor": "blue",
    "name": "Rosanna Mcclure",
    "gender": "female",
    "company": "SUSTENZA",
    "email": "rosannamcclure@sustenza.com",
    "phone": "+1 (828) 600-3155",
    "address": "979 Aster Court, Lupton, District Of Columbia, 301",
    "about": "Ipsum irure Lorem laboris nulla quis. Consectetur quis eu sunt consequat do sunt in officia. Commodo sit aliquip nisi commodo occaecat amet ex ea magna sit ullamco. Eiusmod id duis labore aliqua amet duis excepteur enim elit. Consectetur pariatur ex sunt et ullamco quis.\r\n",
    "registered": "2014-08-22T03:39:26 -06:-30",
    "latitude": 5.274602,
    "longitude": 176.881832,
    "tags": [
      "magna",
      "proident",
      "nulla",
      "labore",
      "elit",
      "ea",
      "proident"
    ],
    "friends": [
      {
        "id": 0,
        "name": "Ramsey Hartman"
      },
      {
        "id": 1,
        "name": "Sallie Mendez"
      },
      {
        "id": 2,
        "name": "Pansy Contreras"
      }
    ],
    "greeting": "Hello, Rosanna Mcclure! You have 6 unread messages.",
    "favoriteFruit": "apple"
  },
  {
    "_id": "5d810b514de3a5fb76b14875",
    "index": 13,
    "guid": "8e2d750c-9c55-4258-82e6-3e4196b29bd2",
    "isActive": true,
    "balance": "$2,181.18",
    "picture": "http://placehold.it/32x32",
    "age": 29,
    "eyeColor": "brown",
    "name": "Liliana Kent",
    "gender": "female",
    "company": "ECOSYS",
    "email": "lilianakent@ecosys.com",
    "phone": "+1 (963) 469-3957",
    "address": "747 McClancy Place, Echo, Georgia, 4956",
    "about": "Enim fugiat aute veniam tempor dolor reprehenderit magna exercitation nisi laborum aliquip ex tempor deserunt. Velit tempor culpa duis ut amet occaecat nostrud deserunt nisi. Quis exercitation esse dolore in mollit Lorem excepteur adipisicing incididunt. Eiusmod sint tempor sunt aliqua ipsum minim minim culpa irure. Nostrud consectetur qui culpa in quis dolore duis.\r\n",
    "registered": "2016-06-06T12:30:39 -06:-30",
    "latitude": 71.617293,
    "longitude": -80.1651,
    "tags": [
      "veniam",
      "labore",
      "laboris",
      "culpa",
      "consequat",
      "anim",
      "in"
    ],
    "friends": [
      {
        "id": 0,
        "name": "Morrison Stevens"
      },
      {
        "id": 1,
        "name": "Kathie Wilkinson"
      },
      {
        "id": 2,
        "name": "Reeves Wiggins"
      }
    ],
    "greeting": "Hello, Liliana Kent! You have 5 unread messages.",
    "favoriteFruit": "strawberry"
  },
  {
    "_id": "5d810b5171459100e01f5cdb",
    "index": 14,
    "guid": "8c891872-04d5-4048-9d1e-f0a20c54dce4",
    "isActive": false,
    "balance": "$3,749.79",
    "picture": "http://placehold.it/32x32",
    "age": 33,
    "eyeColor": "brown",
    "name": "Juanita George",
    "gender": "female",
    "company": "ECRAZE",
    "email": "juanitageorge@ecraze.com",
    "phone": "+1 (834) 409-3445",
    "address": "996 Columbia Street, Manitou, Ohio, 4592",
    "about": "Cupidatat duis cupidatat eu cupidatat dolore aliquip id sit sint enim enim. Culpa in elit eu officia elit ex proident eu minim id incididunt. Eiusmod elit nulla veniam id nisi tempor sint velit laborum consectetur ex. Minim velit nisi cupidatat amet reprehenderit irure labore esse nisi dolor consequat Lorem culpa fugiat.\r\n",
    "registered": "2018-12-17T10:58:21 -06:-30",
    "latitude": -78.148227,
    "longitude": -44.83346,
    "tags": [
      "enim",
      "laborum",
      "duis",
      "quis",
      "sint",
      "culpa",
      "labore"
    ],
    "friends": [
      {
        "id": 0,
        "name": "Lang Daniel"
      },
      {
        "id": 1,
        "name": "Desiree Trevino"
      },
      {
        "id": 2,
        "name": "Hale Downs"
      }
    ],
    "greeting": "Hello, Juanita George! You have 6 unread messages.",
    "favoriteFruit": "strawberry"
  },
  {
    "_id": "5d810b5184964a5bedd014e5",
    "index": 15,
    "guid": "65e4988a-3983-4464-bb18-a56336a757ac",
    "isActive": true,
    "balance": "$2,921.51",
    "picture": "http://placehold.it/32x32",
    "age": 30,
    "eyeColor": "blue",
    "name": "Tillman Medina",
    "gender": "male",
    "company": "GEEKOLA",
    "email": "tillmanmedina@geekola.com",
    "phone": "+1 (977) 454-3325",
    "address": "674 Fay Court, Sunnyside, Maine, 4909",
    "about": "Et consequat consectetur sit laboris veniam ex consectetur est sit. Veniam velit non consectetur reprehenderit. Duis laboris esse eiusmod aliquip sunt veniam Lorem sint nisi exercitation exercitation occaecat magna amet.\r\n",
    "registered": "2016-11-10T02:15:16 -06:-30",
    "latitude": -57.760885,
    "longitude": -134.261748,
    "tags": [
      "id",
      "ea",
      "enim",
      "occaecat",
      "ex",
      "tempor",
      "consectetur"
    ],
    "friends": [
      {
        "id": 0,
        "name": "Lancaster Sullivan"
      },
      {
        "id": 1,
        "name": "Billie Austin"
      },
      {
        "id": 2,
        "name": "Nelda Keith"
      }
    ],
    "greeting": "Hello, Tillman Medina! You have 1 unread messages.",
    "favoriteFruit": "strawberry"
  },
  {
    "_id": "5d810b5171b727b816c775ae",
    "index": 16,
    "guid": "15e925c1-6dce-427b-a2e0-b7635d3970ce",
    "isActive": false,
    "balance": "$1,364.96",
    "picture": "http://placehold.it/32x32",
    "age": 34,
    "eyeColor": "blue",
    "name": "Stephens Jordan",
    "gender": "male",
    "company": "DIGINETIC",
    "email": "stephensjordan@diginetic.com",
    "phone": "+1 (883) 578-2401",
    "address": "684 Cove Lane, Defiance, Utah, 6586",
    "about": "In exercitation et voluptate elit pariatur anim Lorem. Veniam sit velit non ad in adipisicing minim culpa nostrud nisi. Sint deserunt sit in ullamco eiusmod pariatur ea. Labore dolor qui fugiat deserunt fugiat. Velit laborum esse fugiat voluptate aliquip qui do magna et nulla excepteur.\r\n",
    "registered": "2014-10-05T01:55:00 -06:-30",
    "latitude": -54.671073,
    "longitude": -163.144523,
    "tags": [
      "minim",
      "aliqua",
      "aute",
      "proident",
      "sint",
      "commodo",
      "duis"
    ],
    "friends": [
      {
        "id": 0,
        "name": "Jarvis Barnett"
      },
      {
        "id": 1,
        "name": "Suarez Mcfarland"
      },
      {
        "id": 2,
        "name": "Fanny Whitney"
      }
    ],
    "greeting": "Hello, Stephens Jordan! You have 3 unread messages.",
    "favoriteFruit": "apple"
  },
  {
    "_id": "5d810b51ec24d8684032fae2",
    "index": 17,
    "guid": "73b23bc4-b516-4aac-ac15-b3c1a457bfee",
    "isActive": false,
    "balance": "$1,087.81",
    "picture": "http://placehold.it/32x32",
    "age": 37,
    "eyeColor": "blue",
    "name": "Rocha Ellison",
    "gender": "male",
    "company": "XYQAG",
    "email": "rochaellison@xyqag.com",
    "phone": "+1 (869) 519-2356",
    "address": "433 Himrod Street, Cliff, Missouri, 7841",
    "about": "Aliquip Lorem sit reprehenderit esse. Dolor fugiat et occaecat magna aute est velit exercitation. Mollit dolore deserunt culpa ut esse culpa minim ullamco eu mollit occaecat. Consectetur irure officia occaecat officia dolor velit.\r\n",
    "registered": "2017-03-24T07:12:03 -06:-30",
    "latitude": -15.610649,
    "longitude": 72.777055,
    "tags": [
      "fugiat",
      "est",
      "dolore",
      "do",
      "velit",
      "cupidatat",
      "ex"
    ],
    "friends": [
      {
        "id": 0,
        "name": "Clemons Levy"
      },
      {
        "id": 1,
        "name": "Barker Banks"
      },
      {
        "id": 2,
        "name": "Bonita Ballard"
      }
    ],
    "greeting": "Hello, Rocha Ellison! You have 1 unread messages.",
    "favoriteFruit": "strawberry"
  },
  {
    "_id": "5d810b518a87e97c01c01c09",
    "index": 18,
    "guid": "4a414ee3-e52b-4017-97d8-ab3d3ff3c51c",
    "isActive": true,
    "balance": "$2,779.82",
    "picture": "http://placehold.it/32x32",
    "age": 33,
    "eyeColor": "green",
    "name": "Burke Irwin",
    "gender": "male",
    "company": "GINKOGENE",
    "email": "burkeirwin@ginkogene.com",
    "phone": "+1 (853) 471-2926",
    "address": "330 Tabor Court, Stewartville, Louisiana, 740",
    "about": "Aute eiusmod ipsum veniam minim eiusmod ipsum et id deserunt fugiat laboris velit dolore. Officia enim eiusmod cillum culpa adipisicing cupidatat sit duis incididunt cillum qui cillum quis consectetur. Sunt magna ad cillum amet dolore magna sit consectetur magna exercitation id laboris esse. Magna voluptate nostrud aliquip irure do.\r\n",
    "registered": "2019-01-13T07:28:37 -06:-30",
    "latitude": 17.590941,
    "longitude": 167.62354,
    "tags": [
      "minim",
      "ipsum",
      "veniam",
      "amet",
      "aliqua",
      "enim",
      "fugiat"
    ],
    "friends": [
      {
        "id": 0,
        "name": "Deidre Walters"
      },
      {
        "id": 1,
        "name": "Sutton Mccormick"
      },
      {
        "id": 2,
        "name": "Isabella Elliott"
      }
    ],
    "greeting": "Hello, Burke Irwin! You have 4 unread messages.",
    "favoriteFruit": "banana"
  },
  {
    "_id": "5d810b5174f4b8a04b714e52",
    "index": 19,
    "guid": "de38a032-27bd-4169-bd6f-f7eacd57dfb9",
    "isActive": true,
    "balance": "$3,940.33",
    "picture": "http://placehold.it/32x32",
    "age": 30,
    "eyeColor": "green",
    "name": "Maxine Mckee",
    "gender": "female",
    "company": "HOMELUX",
    "email": "maxinemckee@homelux.com",
    "phone": "+1 (818) 430-2591",
    "address": "179 Atkins Avenue, Waumandee, South Dakota, 1628",
    "about": "Est veniam culpa laborum sint cupidatat proident veniam enim duis est commodo quis excepteur. Reprehenderit cillum duis proident cupidatat proident laboris sint. Eiusmod duis cupidatat magna consequat eiusmod ea reprehenderit aute. Voluptate magna nostrud commodo nostrud incididunt consequat consectetur irure.\r\n",
    "registered": "2017-10-18T11:56:49 -06:-30",
    "latitude": -60.414956,
    "longitude": -37.403725,
    "tags": [
      "ea",
      "exercitation",
      "ex",
      "exercitation",
      "excepteur",
      "laborum",
      "dolore"
    ],
    "friends": [
      {
        "id": 0,
        "name": "Melton Hensley"
      },
      {
        "id": 1,
        "name": "Tessa Howe"
      },
      {
        "id": 2,
        "name": "Dalton Haley"
      }
    ],
    "greeting": "Hello, Maxine Mckee! You have 9 unread messages.",
    "favoriteFruit": "banana"
  },
  {
    "_id": "5d810b51c761a59446765dc9",
    "index": 20,
    "guid": "b90f7e81-533f-4413-ae09-fd5c069da053",
    "isActive": true,
    "balance": "$1,579.25",
    "picture": "http://placehold.it/32x32",
    "age": 37,
    "eyeColor": "green",
    "name": "Page Snow",
    "gender": "male",
    "company": "COMBOGENE",
    "email": "pagesnow@combogene.com",
    "phone": "+1 (941) 448-2683",
    "address": "775 Granite Street, Monument, West Virginia, 7668",
    "about": "Consequat reprehenderit ipsum sint pariatur excepteur duis commodo. Aliqua quis et dolor eu ea incididunt excepteur anim Lorem elit quis consequat sint. Amet ad aute duis consequat. Eu magna commodo proident mollit non incididunt excepteur. Velit veniam ea cillum ad commodo eu. Do duis adipisicing adipisicing nostrud eu consectetur ullamco in fugiat amet aute nulla qui.\r\n",
    "registered": "2019-08-11T04:54:02 -06:-30",
    "latitude": 77.751872,
    "longitude": 7.983651,
    "tags": [
      "eu",
      "duis",
      "minim",
      "do",
      "cillum",
      "aute",
      "laborum"
    ],
    "friends": [
      {
        "id": 0,
        "name": "Calhoun Weiss"
      },
      {
        "id": 1,
        "name": "Elvia Carlson"
      },
      {
        "id": 2,
        "name": "Concetta Baird"
      }
    ],
    "greeting": "Hello, Page Snow! You have 9 unread messages.",
    "favoriteFruit": "apple"
  },
  {
    "_id": "5d810b51feac49c50c9970fe",
    "index": 21,
    "guid": "b0ce903e-d98d-46d2-a0e7-9fec339ca6af",
    "isActive": false,
    "balance": "$2,381.84",
    "picture": "http://placehold.it/32x32",
    "age": 37,
    "eyeColor": "green",
    "name": "Leila Gross",
    "gender": "female",
    "company": "SURETECH",
    "email": "leilagross@suretech.com",
    "phone": "+1 (845) 444-3150",
    "address": "785 Broome Street, Goldfield, Federated States Of Micronesia, 3728",
    "about": "Sunt velit non qui pariatur. Consequat eiusmod eu in nulla cupidatat cupidatat velit velit. Nostrud officia non cupidatat duis sint. Commodo ipsum eu laboris Lorem aute nostrud proident minim aute culpa. Eu adipisicing proident consectetur proident commodo esse amet sint velit excepteur esse laboris. Sunt commodo et consectetur nulla magna nostrud enim adipisicing fugiat id. Adipisicing do cillum excepteur veniam aute dolore esse cillum commodo exercitation.\r\n",
    "registered": "2014-07-13T08:57:00 -06:-30",
    "latitude": -54.827029,
    "longitude": -143.596407,
    "tags": [
      "non",
      "id",
      "culpa",
      "incididunt",
      "anim",
      "ipsum",
      "cillum"
    ],
    "friends": [
      {
        "id": 0,
        "name": "Jo Mccarty"
      },
      {
        "id": 1,
        "name": "Maggie Chapman"
      },
      {
        "id": 2,
        "name": "Flossie Avila"
      }
    ],
    "greeting": "Hello, Leila Gross! You have 5 unread messages.",
    "favoriteFruit": "strawberry"
  },
  {
    "_id": "5d810b51374856bba0a90244",
    "index": 22,
    "guid": "4498b03e-e4c1-46ed-8a0e-37a44516ef24",
    "isActive": true,
    "balance": "$2,345.13",
    "picture": "http://placehold.it/32x32",
    "age": 29,
    "eyeColor": "green",
    "name": "Brady Puckett",
    "gender": "male",
    "company": "CENTREE",
    "email": "bradypuckett@centree.com",
    "phone": "+1 (816) 425-2564",
    "address": "507 Bayview Place, Heil, Oregon, 7460",
    "about": "Labore tempor sunt ipsum tempor commodo velit. Fugiat amet fugiat veniam fugiat et consectetur. Sit tempor elit quis minim tempor sint magna dolor consectetur pariatur. Voluptate do cillum Lorem magna do ullamco voluptate eiusmod non. Officia elit esse ipsum ullamco Lorem esse excepteur ea aliqua adipisicing pariatur cupidatat.\r\n",
    "registered": "2014-09-11T11:31:44 -06:-30",
    "latitude": 71.410313,
    "longitude": 29.923171,
    "tags": [
      "ullamco",
      "dolor",
      "irure",
      "ad",
      "incididunt",
      "est",
      "anim"
    ],
    "friends": [
      {
        "id": 0,
        "name": "Carson Ford"
      },
      {
        "id": 1,
        "name": "Thompson Kinney"
      },
      {
        "id": 2,
        "name": "Shelia Parrish"
      }
    ],
    "greeting": "Hello, Brady Puckett! You have 7 unread messages.",
    "favoriteFruit": "banana"
  },
  {
    "_id": "5d810b5170e7ce11ffb2277c",
    "index": 23,
    "guid": "1af5ff4d-2357-4716-ac23-34184201f980",
    "isActive": true,
    "balance": "$1,745.27",
    "picture": "http://placehold.it/32x32",
    "age": 37,
    "eyeColor": "green",
    "name": "Colette Monroe",
    "gender": "female",
    "company": "SOPRANO",
    "email": "colettemonroe@soprano.com",
    "phone": "+1 (906) 597-2388",
    "address": "209 Auburn Place, Bordelonville, Rhode Island, 6169",
    "about": "Dolor voluptate occaecat dolor in exercitation aute. Veniam dolor voluptate nulla ullamco consequat nulla reprehenderit culpa deserunt esse. Eu ea nostrud ea proident nisi.\r\n",
    "registered": "2018-06-11T12:57:51 -06:-30",
    "latitude": -21.217303,
    "longitude": -54.189034,
    "tags": [
      "fugiat",
      "laboris",
      "ex",
      "voluptate",
      "exercitation",
      "nisi",
      "elit"
    ],
    "friends": [
      {
        "id": 0,
        "name": "Walters Dyer"
      },
      {
        "id": 1,
        "name": "Blackburn Branch"
      },
      {
        "id": 2,
        "name": "Diann Neal"
      }
    ],
    "greeting": "Hello, Colette Monroe! You have 2 unread messages.",
    "favoriteFruit": "banana"
  },
  {
    "_id": "5d810b51ab187843fa167625",
    "index": 24,
    "guid": "00337d3e-12ff-4d78-8504-573f99abed51",
    "isActive": false,
    "balance": "$3,631.46",
    "picture": "http://placehold.it/32x32",
    "age": 37,
    "eyeColor": "blue",
    "name": "Adkins Mcpherson",
    "gender": "male",
    "company": "SONIQUE",
    "email": "adkinsmcpherson@sonique.com",
    "phone": "+1 (961) 541-3688",
    "address": "741 Sutter Avenue, Gorham, New Hampshire, 9723",
    "about": "Cillum laboris labore officia laboris irure incididunt sunt laborum quis labore Lorem Lorem reprehenderit elit. Qui sunt tempor anim aute. Ullamco eu id nostrud quis reprehenderit mollit. Nostrud et sit consequat aliqua ullamco ea in cupidatat. Labore quis aute enim ad fugiat elit fugiat dolor nulla voluptate. Eiusmod non est sint culpa voluptate occaecat ad consectetur.\r\n",
    "registered": "2018-04-02T01:38:16 -06:-30",
    "latitude": 29.135041,
    "longitude": 171.446884,
    "tags": [
      "reprehenderit",
      "elit",
      "duis",
      "dolor",
      "aliquip",
      "consequat",
      "ad"
    ],
    "friends": [
      {
        "id": 0,
        "name": "Palmer Mayo"
      },
      {
        "id": 1,
        "name": "Hill Rivas"
      },
      {
        "id": 2,
        "name": "Campbell Hayes"
      }
    ],
    "greeting": "Hello, Adkins Mcpherson! You have 5 unread messages.",
    "favoriteFruit": "apple"
  },
  {
    "_id": "5d810b5137525427690e3594",
    "index": 25,
    "guid": "509eca5f-73d9-4f73-b3d6-5130c26e4b14",
    "isActive": false,
    "balance": "$3,564.85",
    "picture": "http://placehold.it/32x32",
    "age": 25,
    "eyeColor": "green",
    "name": "Ingram Knowles",
    "gender": "male",
    "company": "CANDECOR",
    "email": "ingramknowles@candecor.com",
    "phone": "+1 (876) 518-2848",
    "address": "739 Prospect Avenue, Townsend, Mississippi, 7926",
    "about": "Ea occaecat Lorem eiusmod tempor nisi esse in dolore voluptate elit amet ea cupidatat. Incididunt deserunt ipsum id veniam culpa qui magna aute quis. Fugiat in duis non dolore laborum sit ut non do mollit. Lorem aliquip culpa ex est labore aliqua eiusmod duis.\r\n",
    "registered": "2016-09-02T04:45:08 -06:-30",
    "latitude": 70.681183,
    "longitude": -94.669075,
    "tags": [
      "culpa",
      "sint",
      "veniam",
      "enim",
      "cupidatat",
      "est",
      "ex"
    ],
    "friends": [
      {
        "id": 0,
        "name": "Stacie Rivera"
      },
      {
        "id": 1,
        "name": "Ora Hines"
      },
      {
        "id": 2,
        "name": "Humphrey Marks"
      }
    ],
    "greeting": "Hello, Ingram Knowles! You have 9 unread messages.",
    "favoriteFruit": "apple"
  },
  {
    "_id": "5d810b51cf1394e137c3c1d1",
    "index": 26,
    "guid": "a13ac279-0563-4840-86a9-1ed072cade13",
    "isActive": false,
    "balance": "$3,384.78",
    "picture": "http://placehold.it/32x32",
    "age": 38,
    "eyeColor": "brown",
    "name": "Helena Vega",
    "gender": "female",
    "company": "TUBESYS",
    "email": "helenavega@tubesys.com",
    "phone": "+1 (871) 494-2095",
    "address": "428 Arlington Avenue, Gasquet, Puerto Rico, 6196",
    "about": "Cupidatat labore et adipisicing quis tempor pariatur magna aliquip minim voluptate consectetur sunt id Lorem. Ullamco laboris commodo anim id ut cillum enim nisi dolor duis anim ullamco commodo. Cupidatat id aliqua ex occaecat. Ipsum laborum laborum proident irure voluptate ullamco elit labore amet culpa aliquip esse veniam nulla.\r\n",
    "registered": "2019-06-27T07:59:22 -06:-30",
    "latitude": -27.826587,
    "longitude": -148.977927,
    "tags": [
      "irure",
      "officia",
      "cillum",
      "qui",
      "sit",
      "Lorem",
      "consequat"
    ],
    "friends": [
      {
        "id": 0,
        "name": "Benita Schmidt"
      },
      {
        "id": 1,
        "name": "Faith Craig"
      },
      {
        "id": 2,
        "name": "Salazar Fitzpatrick"
      }
    ],
    "greeting": "Hello, Helena Vega! You have 2 unread messages.",
    "favoriteFruit": "strawberry"
  },
  {
    "_id": "5d810b51804838cc70bb1384",
    "index": 27,
    "guid": "605835df-ef6f-4ad8-8206-11f95915ab34",
    "isActive": true,
    "balance": "$1,783.28",
    "picture": "http://placehold.it/32x32",
    "age": 22,
    "eyeColor": "blue",
    "name": "Nina Dennis",
    "gender": "female",
    "company": "FURNITECH",
    "email": "ninadennis@furnitech.com",
    "phone": "+1 (827) 500-2186",
    "address": "741 Hart Place, Muse, Vermont, 9020",
    "about": "Eiusmod labore enim incididunt fugiat. Ea non amet deserunt anim. Aliquip occaecat dolor incididunt voluptate nostrud exercitation anim velit. Anim labore mollit nulla anim aute esse ullamco. Laborum laborum cillum cillum aute ullamco adipisicing minim est labore.\r\n",
    "registered": "2016-04-24T09:28:09 -06:-30",
    "latitude": -89.314559,
    "longitude": -57.097571,
    "tags": [
      "officia",
      "consectetur",
      "ut",
      "Lorem",
      "esse",
      "esse",
      "irure"
    ],
    "friends": [
      {
        "id": 0,
        "name": "Anastasia Rhodes"
      },
      {
        "id": 1,
        "name": "Tyler Livingston"
      },
      {
        "id": 2,
        "name": "Eddie Wynn"
      }
    ],
    "greeting": "Hello, Nina Dennis! You have 7 unread messages.",
    "favoriteFruit": "apple"
  },
  {
    "_id": "5d810b5186478cab4f6967f7",
    "index": 28,
    "guid": "03071ba8-2a7e-49db-bc64-d49824eeb146",
    "isActive": false,
    "balance": "$3,283.43",
    "picture": "http://placehold.it/32x32",
    "age": 36,
    "eyeColor": "green",
    "name": "Rhoda Becker",
    "gender": "female",
    "company": "KRAGGLE",
    "email": "rhodabecker@kraggle.com",
    "phone": "+1 (980) 423-2015",
    "address": "564 Argyle Road, Hiseville, Maryland, 8791",
    "about": "Pariatur dolor mollit adipisicing minim laboris. Sunt ea in anim enim aute ex Lorem cillum pariatur. Qui ad et exercitation est eu labore deserunt labore nisi labore consectetur magna aliquip sit. Commodo proident adipisicing labore ullamco tempor ipsum. Veniam sunt Lorem qui aliquip duis et. Sit elit proident commodo reprehenderit nulla cillum Lorem anim proident sunt reprehenderit. Commodo magna reprehenderit magna consequat proident do.\r\n",
    "registered": "2016-04-18T06:57:07 -06:-30",
    "latitude": 15.2664,
    "longitude": 120.679886,
    "tags": [
      "culpa",
      "eu",
      "commodo",
      "id",
      "amet",
      "magna",
      "nisi"
    ],
    "friends": [
      {
        "id": 0,
        "name": "Sylvia Cantu"
      },
      {
        "id": 1,
        "name": "Hester Cotton"
      },
      {
        "id": 2,
        "name": "Nieves Chaney"
      }
    ],
    "greeting": "Hello, Rhoda Becker! You have 5 unread messages.",
    "favoriteFruit": "strawberry"
  },
  {
    "_id": "5d810b5121b69e35cecf0f84",
    "index": 29,
    "guid": "c3d296a8-d57f-4eeb-a765-968699178829",
    "isActive": true,
    "balance": "$3,420.19",
    "picture": "http://placehold.it/32x32",
    "age": 36,
    "eyeColor": "blue",
    "name": "Jodi Mcmahon",
    "gender": "female",
    "company": "OMNIGOG",
    "email": "jodimcmahon@omnigog.com",
    "phone": "+1 (812) 593-3275",
    "address": "715 Suydam Street, Worton, Hawaii, 9613",
    "about": "Anim aute mollit exercitation id labore fugiat commodo ad exercitation cupidatat excepteur culpa aute. Nulla ipsum ipsum labore id aliquip. Enim minim excepteur amet reprehenderit et est.\r\n",
    "registered": "2017-05-13T04:14:00 -06:-30",
    "latitude": -54.160158,
    "longitude": -163.567129,
    "tags": [
      "consectetur",
      "incididunt",
      "proident",
      "pariatur",
      "ea",
      "voluptate",
      "deserunt"
    ],
    "friends": [
      {
        "id": 0,
        "name": "Short Parsons"
      },
      {
        "id": 1,
        "name": "Priscilla Browning"
      },
      {
        "id": 2,
        "name": "Vanessa Hale"
      }
    ],
    "greeting": "Hello, Jodi Mcmahon! You have 1 unread messages.",
    "favoriteFruit": "strawberry"
  },
  {
    "_id": "5d810b515397039820387809",
    "index": 30,
    "guid": "e134a7a2-f1d5-48dc-adfc-a07aca46c4dc",
    "isActive": true,
    "balance": "$1,020.80",
    "picture": "http://placehold.it/32x32",
    "age": 33,
    "eyeColor": "green",
    "name": "Courtney Gibbs",
    "gender": "female",
    "company": "XYLAR",
    "email": "courtneygibbs@xylar.com",
    "phone": "+1 (934) 494-2269",
    "address": "881 Hendrickson Place, Alleghenyville, Connecticut, 4357",
    "about": "Ea reprehenderit incididunt mollit minim eiusmod ipsum est culpa. Laboris excepteur do culpa commodo in consectetur est esse ad laborum. Dolor esse id ea est tempor aute.\r\n",
    "registered": "2017-05-21T06:54:15 -06:-30",
    "latitude": 47.216048,
    "longitude": -8.333852,
    "tags": [
      "amet",
      "laboris",
      "cupidatat",
      "incididunt",
      "tempor",
      "officia",
      "minim"
    ],
    "friends": [
      {
        "id": 0,
        "name": "Martina Marquez"
      },
      {
        "id": 1,
        "name": "Meagan Clemons"
      },
      {
        "id": 2,
        "name": "Day Maldonado"
      }
    ],
    "greeting": "Hello, Courtney Gibbs! You have 1 unread messages.",
    "favoriteFruit": "banana"
  },
  {
    "_id": "5d810b515a039d6512059642",
    "index": 31,
    "guid": "ca144d91-8619-475d-952a-30d014dddd5a",
    "isActive": false,
    "balance": "$3,436.59",
    "picture": "http://placehold.it/32x32",
    "age": 31,
    "eyeColor": "brown",
    "name": "Gale Buckley",
    "gender": "female",
    "company": "FORTEAN",
    "email": "galebuckley@fortean.com",
    "phone": "+1 (929) 442-4000",
    "address": "899 Hall Street, Chalfant, Virginia, 7923",
    "about": "Tempor nulla mollit eiusmod deserunt irure ullamco Lorem id dolore enim id voluptate exercitation cupidatat. Commodo duis non anim duis enim velit nostrud fugiat minim excepteur. Velit proident id anim voluptate non occaecat amet tempor ad nisi. Aliqua pariatur pariatur ut excepteur tempor. Qui nisi dolore adipisicing consectetur dolore officia quis veniam et officia. Est non in consectetur mollit esse exercitation voluptate qui dolor enim. Duis nulla dolore ullamco fugiat mollit tempor.\r\n",
    "registered": "2015-11-12T04:50:32 -06:-30",
    "latitude": -2.358225,
    "longitude": -49.899455,
    "tags": [
      "eu",
      "labore",
      "sit",
      "pariatur",
      "nostrud",
      "ullamco",
      "aliqua"
    ],
    "friends": [
      {
        "id": 0,
        "name": "Denise Cole"
      },
      {
        "id": 1,
        "name": "Estella Rojas"
      },
      {
        "id": 2,
        "name": "Thelma Dunlap"
      }
    ],
    "greeting": "Hello, Gale Buckley! You have 1 unread messages.",
    "favoriteFruit": "apple"
  },
  {
    "_id": "5d810b51105272c14f2748c2",
    "index": 32,
    "guid": "b9ea961a-6cb8-4ef2-9db4-b00092dfa3ac",
    "isActive": true,
    "balance": "$2,407.92",
    "picture": "http://placehold.it/32x32",
    "age": 21,
    "eyeColor": "brown",
    "name": "Trisha Pope",
    "gender": "female",
    "company": "INSURON",
    "email": "trishapope@insuron.com",
    "phone": "+1 (895) 496-2992",
    "address": "617 Richmond Street, Accoville, Montana, 7445",
    "about": "Duis id aute commodo cupidatat. Voluptate velit occaecat consequat tempor eu pariatur nulla nulla tempor exercitation reprehenderit. Tempor eiusmod non magna pariatur aliqua dolore ullamco consectetur adipisicing incididunt laboris qui dolore laborum. Aute ad dolor reprehenderit ea ea sint anim pariatur aliquip. Dolor sit elit enim dolor consectetur.\r\n",
    "registered": "2019-05-27T05:20:30 -06:-30",
    "latitude": -25.368236,
    "longitude": 150.935466,
    "tags": [
      "proident",
      "fugiat",
      "tempor",
      "laboris",
      "non",
      "dolor",
      "reprehenderit"
    ],
    "friends": [
      {
        "id": 0,
        "name": "Hope Santos"
      },
      {
        "id": 1,
        "name": "Webster Beach"
      },
      {
        "id": 2,
        "name": "Schmidt Shaffer"
      }
    ],
    "greeting": "Hello, Trisha Pope! You have 5 unread messages.",
    "favoriteFruit": "apple"
  },
  {
    "_id": "5d810b51842e5b3e02919e1a",
    "index": 33,
    "guid": "358442e1-b223-40b2-b583-0247d1da72d5",
    "isActive": true,
    "balance": "$1,267.45",
    "picture": "http://placehold.it/32x32",
    "age": 40,
    "eyeColor": "blue",
    "name": "Caitlin Walton",
    "gender": "female",
    "company": "GROK",
    "email": "caitlinwalton@grok.com",
    "phone": "+1 (957) 488-3581",
    "address": "109 Brighton Avenue, Vivian, Wyoming, 2668",
    "about": "Voluptate eu consectetur cupidatat voluptate nisi ad amet incididunt est labore nostrud anim officia. Nostrud esse cupidatat laborum minim aliqua. In exercitation fugiat laborum sunt. Amet nulla in sit ullamco consectetur aliqua sunt Lorem sunt aliqua. Sit id deserunt cupidatat elit. Deserunt nostrud cillum ad cillum mollit dolor adipisicing exercitation ipsum. Duis reprehenderit elit veniam cillum.\r\n",
    "registered": "2016-07-17T02:39:38 -06:-30",
    "latitude": 5.14752,
    "longitude": -130.255803,
    "tags": [
      "enim",
      "deserunt",
      "magna",
      "sint",
      "dolor",
      "pariatur",
      "exercitation"
    ],
    "friends": [
      {
        "id": 0,
        "name": "Church Richards"
      },
      {
        "id": 1,
        "name": "Gutierrez David"
      },
      {
        "id": 2,
        "name": "Leslie Roberson"
      }
    ],
    "greeting": "Hello, Caitlin Walton! You have 8 unread messages.",
    "favoriteFruit": "banana"
  },
  {
    "_id": "5d810b51eaf605e06f355f55",
    "index": 34,
    "guid": "cb4e06d5-a091-4d73-a6bb-e921c2bf52a5",
    "isActive": true,
    "balance": "$2,500.33",
    "picture": "http://placehold.it/32x32",
    "age": 36,
    "eyeColor": "green",
    "name": "Hood Garrett",
    "gender": "male",
    "company": "PHOTOBIN",
    "email": "hoodgarrett@photobin.com",
    "phone": "+1 (986) 473-3863",
    "address": "645 Elm Avenue, Gibsonia, New York, 2003",
    "about": "Officia dolore aute exercitation amet ea enim ipsum adipisicing dolor eiusmod eu commodo. Ipsum sit proident quis anim labore culpa consectetur consectetur eiusmod nulla ut do irure incididunt. Elit incididunt adipisicing amet reprehenderit consectetur exercitation non cillum cillum dolor duis officia ea.\r\n",
    "registered": "2014-11-13T03:02:57 -06:-30",
    "latitude": -11.66334,
    "longitude": -117.116044,
    "tags": [
      "occaecat",
      "aliquip",
      "in",
      "sint",
      "velit",
      "anim",
      "quis"
    ],
    "friends": [
      {
        "id": 0,
        "name": "Henderson Dickson"
      },
      {
        "id": 1,
        "name": "Briggs Simpson"
      },
      {
        "id": 2,
        "name": "Jamie Gallagher"
      }
    ],
    "greeting": "Hello, Hood Garrett! You have 6 unread messages.",
    "favoriteFruit": "apple"
  },
  {
    "_id": "5d810b51342145e4ce485326",
    "index": 35,
    "guid": "48fc11d9-af96-417c-bcdd-336da4f7ba55",
    "isActive": false,
    "balance": "$2,739.78",
    "picture": "http://placehold.it/32x32",
    "age": 35,
    "eyeColor": "blue",
    "name": "Jodie Norman",
    "gender": "female",
    "company": "MAINELAND",
    "email": "jodienorman@maineland.com",
    "phone": "+1 (957) 536-2973",
    "address": "329 Dooley Street, Saddlebrooke, California, 1975",
    "about": "Ex commodo laborum quis adipisicing cupidatat irure. Quis elit officia occaecat dolor dolor adipisicing ut cillum officia proident ad. Do consectetur nisi elit commodo ut dolor.\r\n",
    "registered": "2017-09-26T08:14:05 -06:-30",
    "latitude": -43.975443,
    "longitude": 178.700142,
    "tags": [
      "culpa",
      "ipsum",
      "ea",
      "ut",
      "eiusmod",
      "sit",
      "esse"
    ],
    "friends": [
      {
        "id": 0,
        "name": "House Anderson"
      },
      {
        "id": 1,
        "name": "Everett Wiley"
      },
      {
        "id": 2,
        "name": "Terrie Mcguire"
      }
    ],
    "greeting": "Hello, Jodie Norman! You have 6 unread messages.",
    "favoriteFruit": "banana"
  },
  {
    "_id": "5d810b513e95ee50abc735bf",
    "index": 36,
    "guid": "a7cd1f69-f5d3-474d-a501-229146805dbb",
    "isActive": true,
    "balance": "$3,619.48",
    "picture": "http://placehold.it/32x32",
    "age": 36,
    "eyeColor": "blue",
    "name": "Hughes Conway",
    "gender": "male",
    "company": "MEDIFAX",
    "email": "hughesconway@medifax.com",
    "phone": "+1 (969) 427-2697",
    "address": "589 Interborough Parkway, Crown, Delaware, 8632",
    "about": "Duis veniam ex ex amet pariatur tempor. Do aliquip nulla amet incididunt ullamco nostrud laborum ad amet. Nostrud reprehenderit irure duis cupidatat labore quis elit quis nulla id. Eu elit dolore eiusmod pariatur amet minim consectetur magna sit pariatur et esse.\r\n",
    "registered": "2018-01-17T11:29:01 -06:-30",
    "latitude": -6.977615,
    "longitude": 150.462749,
    "tags": [
      "velit",
      "mollit",
      "do",
      "elit",
      "voluptate",
      "non",
      "irure"
    ],
    "friends": [
      {
        "id": 0,
        "name": "Black Logan"
      },
      {
        "id": 1,
        "name": "Silva Stephens"
      },
      {
        "id": 2,
        "name": "Susanne Moses"
      }
    ],
    "greeting": "Hello, Hughes Conway! You have 4 unread messages.",
    "favoriteFruit": "banana"
  },
  {
    "_id": "5d810b5185eef3762a3354e5",
    "index": 37,
    "guid": "81f19bee-0947-4fad-9f08-8d12ea1dff4c",
    "isActive": true,
    "balance": "$2,697.40",
    "picture": "http://placehold.it/32x32",
    "age": 34,
    "eyeColor": "blue",
    "name": "Workman Macias",
    "gender": "male",
    "company": "COMCUBINE",
    "email": "workmanmacias@comcubine.com",
    "phone": "+1 (835) 419-2256",
    "address": "948 Ocean Avenue, Elbert, New Mexico, 2841",
    "about": "Culpa est dolore consectetur in ad nisi commodo est fugiat minim. Mollit exercitation sint et nostrud enim non nisi aute amet sint consectetur excepteur. Ad dolore laborum eiusmod Lorem elit eu commodo exercitation in ut eu. Excepteur do mollit consequat incididunt est cillum sint Lorem officia exercitation cupidatat. Elit qui sit sunt anim anim consectetur sit labore. Occaecat laborum ea officia sint id in.\r\n",
    "registered": "2016-08-28T03:51:38 -06:-30",
    "latitude": -86.377626,
    "longitude": -155.658015,
    "tags": [
      "velit",
      "aliqua",
      "do",
      "ea",
      "Lorem",
      "ex",
      "Lorem"
    ],
    "friends": [
      {
        "id": 0,
        "name": "Miriam Mooney"
      },
      {
        "id": 1,
        "name": "Wells Hurst"
      },
      {
        "id": 2,
        "name": "Harper Barron"
      }
    ],
    "greeting": "Hello, Workman Macias! You have 9 unread messages.",
    "favoriteFruit": "banana"
  },
  {
    "_id": "5d810b51dd3dc3a0e85809b9",
    "index": 38,
    "guid": "f6c9c89a-0dee-4bd0-a984-9616e6221c66",
    "isActive": true,
    "balance": "$1,954.43",
    "picture": "http://placehold.it/32x32",
    "age": 20,
    "eyeColor": "green",
    "name": "Riggs Walker",
    "gender": "male",
    "company": "ANIXANG",
    "email": "riggswalker@anixang.com",
    "phone": "+1 (888) 421-2491",
    "address": "418 Oakland Place, Snelling, South Carolina, 5247",
    "about": "Non labore tempor sint cillum tempor consequat sunt in Lorem sunt. Officia esse esse ut elit sit laborum cillum proident minim tempor nulla veniam officia. Exercitation sint sint labore aliquip dolore. Pariatur non ea est pariatur.\r\n",
    "registered": "2019-05-08T10:20:10 -06:-30",
    "latitude": 5.815494,
    "longitude": 128.552001,
    "tags": [
      "velit",
      "elit",
      "adipisicing",
      "eiusmod",
      "deserunt",
      "laboris",
      "non"
    ],
    "friends": [
      {
        "id": 0,
        "name": "Ronda Flowers"
      },
      {
        "id": 1,
        "name": "Lauri Sutton"
      },
      {
        "id": 2,
        "name": "Jeanie Fernandez"
      }
    ],
    "greeting": "Hello, Riggs Walker! You have 2 unread messages.",
    "favoriteFruit": "strawberry"
  },
  {
    "_id": "5d810b51a2f638cb6ef3dda3",
    "index": 39,
    "guid": "e532319d-fc07-4b14-bf72-e3434f0e8ae1",
    "isActive": false,
    "balance": "$1,338.17",
    "picture": "http://placehold.it/32x32",
    "age": 31,
    "eyeColor": "blue",
    "name": "Emma Terry",
    "gender": "female",
    "company": "STOCKPOST",
    "email": "emmaterry@stockpost.com",
    "phone": "+1 (962) 433-2653",
    "address": "293 Varick Avenue, Jardine, Kentucky, 8108",
    "about": "Aute aliqua esse laboris duis. Deserunt incididunt eu adipisicing ea in mollit anim voluptate. Mollit sunt excepteur do proident esse est do velit dolore. Sit cillum eu mollit incididunt voluptate exercitation anim cillum consectetur fugiat.\r\n",
    "registered": "2016-11-05T06:15:50 -06:-30",
    "latitude": -4.361476,
    "longitude": -107.465893,
    "tags": [
      "ipsum",
      "nostrud",
      "anim",
      "ipsum",
      "sint",
      "quis",
      "veniam"
    ],
    "friends": [
      {
        "id": 0,
        "name": "Wolf Mullins"
      },
      {
        "id": 1,
        "name": "May Castaneda"
      },
      {
        "id": 2,
        "name": "Natalia Kaufman"
      }
    ],
    "greeting": "Hello, Emma Terry! You have 3 unread messages.",
    "favoriteFruit": "apple"
  },
  {
    "_id": "5d810b519d73ddeaa654512a",
    "index": 40,
    "guid": "5ba15c32-9cb0-4875-a55a-0129dd8eaa7b",
    "isActive": true,
    "balance": "$2,525.17",
    "picture": "http://placehold.it/32x32",
    "age": 37,
    "eyeColor": "blue",
    "name": "Mcmahon Copeland",
    "gender": "male",
    "company": "INTERODEO",
    "email": "mcmahoncopeland@interodeo.com",
    "phone": "+1 (825) 463-3442",
    "address": "240 Otsego Street, Smeltertown, Marshall Islands, 2362",
    "about": "Ea consectetur in ut commodo et non consequat aute Lorem commodo aliquip. Lorem tempor laboris sunt est nostrud excepteur ea ullamco incididunt id consequat. Qui magna amet anim cillum voluptate nisi non nostrud culpa ullamco sunt sint in sunt. Aliqua qui est commodo ad id ad consequat velit do ad cillum cillum. Sit veniam adipisicing ad labore anim eiusmod anim in Lorem eiusmod ipsum dolore eiusmod. Sit aute consequat voluptate minim minim consectetur incididunt cillum elit mollit labore ea. Aliqua eu dolore duis quis eiusmod commodo adipisicing enim velit quis anim commodo quis sint.\r\n",
    "registered": "2016-11-13T01:27:37 -06:-30",
    "latitude": 32.529014,
    "longitude": -118.423519,
    "tags": [
      "consectetur",
      "sint",
      "excepteur",
      "proident",
      "duis",
      "eu",
      "mollit"
    ],
    "friends": [
      {
        "id": 0,
        "name": "Camille Roman"
      },
      {
        "id": 1,
        "name": "Nannie Goodman"
      },
      {
        "id": 2,
        "name": "Mcfarland Murphy"
      }
    ],
    "greeting": "Hello, Mcmahon Copeland! You have 10 unread messages.",
    "favoriteFruit": "strawberry"
  },
  {
    "_id": "5d810b518bf82eb46dfa165c",
    "index": 41,
    "guid": "778a0cea-c3a3-43da-b9e4-cc65bb32b4d2",
    "isActive": false,
    "balance": "$3,178.99",
    "picture": "http://placehold.it/32x32",
    "age": 35,
    "eyeColor": "blue",
    "name": "Dale Rice",
    "gender": "male",
    "company": "ANIMALIA",
    "email": "dalerice@animalia.com",
    "phone": "+1 (965) 423-2622",
    "address": "568 Hopkins Street, Aberdeen, Virgin Islands, 7588",
    "about": "Proident occaecat laboris tempor voluptate amet elit. Ut laborum elit adipisicing laborum voluptate qui elit veniam deserunt. Culpa culpa reprehenderit nulla exercitation. Aliquip ipsum nisi tempor officia dolor dolore anim duis reprehenderit anim dolor velit sunt labore. Excepteur adipisicing occaecat ullamco nisi ea velit.\r\n",
    "registered": "2018-11-15T12:59:24 -06:-30",
    "latitude": 38.827156,
    "longitude": 117.061633,
    "tags": [
      "nostrud",
      "tempor",
      "anim",
      "ea",
      "labore",
      "anim",
      "officia"
    ],
    "friends": [
      {
        "id": 0,
        "name": "Baird Ball"
      },
      {
        "id": 1,
        "name": "Dean Bullock"
      },
      {
        "id": 2,
        "name": "Patterson Benson"
      }
    ],
    "greeting": "Hello, Dale Rice! You have 6 unread messages.",
    "favoriteFruit": "strawberry"
  },
  {
    "_id": "5d810b51ebcba8d9a3029f8f",
    "index": 42,
    "guid": "88d18728-67fc-4515-9ca7-ad82ce18d172",
    "isActive": true,
    "balance": "$3,346.77",
    "picture": "http://placehold.it/32x32",
    "age": 20,
    "eyeColor": "brown",
    "name": "Dillard Cooley",
    "gender": "male",
    "company": "BEDLAM",
    "email": "dillardcooley@bedlam.com",
    "phone": "+1 (849) 599-2449",
    "address": "762 Chester Street, Dante, Arkansas, 3532",
    "about": "Eu minim adipisicing enim labore occaecat ex. Quis sint deserunt reprehenderit culpa adipisicing id sint tempor. Adipisicing quis est mollit sit incididunt labore laborum ea.\r\n",
    "registered": "2019-02-12T02:53:36 -06:-30",
    "latitude": 14.714432,
    "longitude": -106.520122,
    "tags": [
      "adipisicing",
      "pariatur",
      "ipsum",
      "excepteur",
      "minim",
      "deserunt",
      "ad"
    ],
    "friends": [
      {
        "id": 0,
        "name": "Margie Myers"
      },
      {
        "id": 1,
        "name": "Fay Dean"
      },
      {
        "id": 2,
        "name": "Patton Frank"
      }
    ],
    "greeting": "Hello, Dillard Cooley! You have 10 unread messages.",
    "favoriteFruit": "apple"
  },
  {
    "_id": "5d810b516a916cc1c5913e9c",
    "index": 43,
    "guid": "18fb4223-8462-4703-b8c8-ed9132f0de53",
    "isActive": false,
    "balance": "$1,120.37",
    "picture": "http://placehold.it/32x32",
    "age": 40,
    "eyeColor": "brown",
    "name": "Holmes Alston",
    "gender": "male",
    "company": "BRAINCLIP",
    "email": "holmesalston@brainclip.com",
    "phone": "+1 (888) 573-2594",
    "address": "734 Ruby Street, Bradenville, Florida, 221",
    "about": "Veniam ullamco aliqua proident aliquip ea dolore quis. Anim labore aliqua dolor excepteur enim pariatur. Dolore consectetur do fugiat exercitation occaecat officia. Deserunt aute duis irure est dolore nulla do esse.\r\n",
    "registered": "2015-04-29T03:35:46 -06:-30",
    "latitude": 38.380604,
    "longitude": -34.527158,
    "tags": [
      "qui",
      "voluptate",
      "reprehenderit",
      "amet",
      "eu",
      "quis",
      "ea"
    ],
    "friends": [
      {
        "id": 0,
        "name": "Simone Conley"
      },
      {
        "id": 1,
        "name": "Raymond Koch"
      },
      {
        "id": 2,
        "name": "Dona Winters"
      }
    ],
    "greeting": "Hello, Holmes Alston! You have 6 unread messages.",
    "favoriteFruit": "strawberry"
  },
  {
    "_id": "5d810b51bb9792992930036b",
    "index": 44,
    "guid": "7408c266-0259-4237-b0e7-68addcf018a7",
    "isActive": false,
    "balance": "$1,099.01",
    "picture": "http://placehold.it/32x32",
    "age": 30,
    "eyeColor": "brown",
    "name": "Yvette Warren",
    "gender": "female",
    "company": "EXOBLUE",
    "email": "yvettewarren@exoblue.com",
    "phone": "+1 (942) 506-3382",
    "address": "220 Schroeders Avenue, Bascom, Minnesota, 4901",
    "about": "Sint eu velit adipisicing exercitation sint incididunt irure adipisicing qui id id. Quis commodo mollit deserunt elit laborum irure et. Sit elit anim est culpa dolor eiusmod eu et consequat enim. Sunt ullamco ullamco elit aliqua irure in. Laborum eiusmod magna est aliquip nulla eu. Proident Lorem id reprehenderit ut.\r\n",
    "registered": "2017-03-31T06:05:28 -06:-30",
    "latitude": -87.964154,
    "longitude": 32.309247,
    "tags": [
      "enim",
      "eiusmod",
      "sunt",
      "consectetur",
      "proident",
      "sint",
      "aliquip"
    ],
    "friends": [
      {
        "id": 0,
        "name": "Annmarie Simon"
      },
      {
        "id": 1,
        "name": "Stein Morgan"
      },
      {
        "id": 2,
        "name": "Shirley Sykes"
      }
    ],
    "greeting": "Hello, Yvette Warren! You have 6 unread messages.",
    "favoriteFruit": "strawberry"
  },
  {
    "_id": "5d810b515b7b5f145f7814e9",
    "index": 45,
    "guid": "4fe79dee-912e-45a1-86cd-bdf4a3fb92e0",
    "isActive": false,
    "balance": "$3,418.78",
    "picture": "http://placehold.it/32x32",
    "age": 26,
    "eyeColor": "blue",
    "name": "Holden Sherman",
    "gender": "male",
    "company": "CONJURICA",
    "email": "holdensherman@conjurica.com",
    "phone": "+1 (893) 431-2781",
    "address": "514 Heath Place, Colton, North Carolina, 555",
    "about": "Nisi deserunt pariatur voluptate ex. Consectetur Lorem deserunt dolore et ex qui minim do elit. Irure cillum deserunt non labore id dolore quis quis do dolor.\r\n",
    "registered": "2015-06-16T09:32:52 -06:-30",
    "latitude": 89.927881,
    "longitude": 63.729547,
    "tags": [
      "ullamco",
      "eiusmod",
      "est",
      "tempor",
      "do",
      "reprehenderit",
      "consectetur"
    ],
    "friends": [
      {
        "id": 0,
        "name": "Ebony Snider"
      },
      {
        "id": 1,
        "name": "Diaz Farmer"
      },
      {
        "id": 2,
        "name": "Mcclure Russo"
      }
    ],
    "greeting": "Hello, Holden Sherman! You have 7 unread messages.",
    "favoriteFruit": "apple"
  },
  {
    "_id": "5d810b51b1771bbe23d2cdb1",
    "index": 46,
    "guid": "73ff01d7-86b3-477b-bffb-ef44b9643fdf",
    "isActive": false,
    "balance": "$3,957.56",
    "picture": "http://placehold.it/32x32",
    "age": 39,
    "eyeColor": "blue",
    "name": "Case Vance",
    "gender": "male",
    "company": "ELPRO",
    "email": "casevance@elpro.com",
    "phone": "+1 (984) 588-3939",
    "address": "720 Albemarle Road, Loretto, Guam, 7398",
    "about": "Quis mollit incididunt reprehenderit excepteur sunt ullamco officia occaecat ad aliqua ullamco anim eiusmod commodo. Eu laborum ipsum in adipisicing excepteur excepteur anim commodo consequat anim nostrud tempor laboris ipsum. Amet ut dolore et sit ex aute ullamco consequat magna ut ea.\r\n",
    "registered": "2014-12-20T02:58:39 -06:-30",
    "latitude": 50.949068,
    "longitude": -22.563519,
    "tags": [
      "aute",
      "qui",
      "eiusmod",
      "aute",
      "velit",
      "et",
      "sunt"
    ],
    "friends": [
      {
        "id": 0,
        "name": "Watson Everett"
      },
      {
        "id": 1,
        "name": "Fernandez Welch"
      },
      {
        "id": 2,
        "name": "Contreras Burks"
      }
    ],
    "greeting": "Hello, Case Vance! You have 4 unread messages.",
    "favoriteFruit": "apple"
  },
  {
    "_id": "5d810b514c57cc8b60ee126d",
    "index": 47,
    "guid": "7be04eb7-81e9-4d8a-994d-574b65c05add",
    "isActive": true,
    "balance": "$2,886.15",
    "picture": "http://placehold.it/32x32",
    "age": 24,
    "eyeColor": "brown",
    "name": "Karin Shields",
    "gender": "female",
    "company": "BARKARAMA",
    "email": "karinshields@barkarama.com",
    "phone": "+1 (864) 473-3129",
    "address": "134 Murdock Court, Weeksville, Michigan, 7652",
    "about": "Adipisicing velit ipsum anim nisi do culpa veniam occaecat proident anim aliquip aliquip irure. Reprehenderit minim mollit in excepteur velit esse. Commodo aute et excepteur veniam. Exercitation sit laboris officia voluptate nulla veniam ipsum esse dolor adipisicing excepteur sunt. Commodo sit consectetur reprehenderit sunt proident sit. Sit aliquip ipsum excepteur velit aute aute irure esse tempor non velit dolor. Ex aute veniam aliqua consequat.\r\n",
    "registered": "2018-04-16T02:11:02 -06:-30",
    "latitude": 6.855455,
    "longitude": -119.137443,
    "tags": [
      "occaecat",
      "aute",
      "laborum",
      "consequat",
      "cillum",
      "laborum",
      "est"
    ],
    "friends": [
      {
        "id": 0,
        "name": "Dorthy Wilkins"
      },
      {
        "id": 1,
        "name": "Mccarthy Cummings"
      },
      {
        "id": 2,
        "name": "Kelsey Mcmillan"
      }
    ],
    "greeting": "Hello, Karin Shields! You have 3 unread messages.",
    "favoriteFruit": "banana"
  },
  {
    "_id": "5d810b511bf8c4ef2f028086",
    "index": 48,
    "guid": "893713e9-3006-43b8-823e-ed3e1a5bc3d0",
    "isActive": false,
    "balance": "$2,477.83",
    "picture": "http://placehold.it/32x32",
    "age": 30,
    "eyeColor": "green",
    "name": "Buckner Velez",
    "gender": "male",
    "company": "ZENTURY",
    "email": "bucknervelez@zentury.com",
    "phone": "+1 (976) 489-2268",
    "address": "698 George Street, Brazos, Arizona, 5694",
    "about": "Velit excepteur occaecat aute sint deserunt irure. Ad ut aliquip deserunt quis ut nulla eiusmod ex aliqua. Mollit quis veniam laborum fugiat pariatur sunt id tempor sint reprehenderit laboris deserunt occaecat. Adipisicing duis quis sunt elit. Sunt tempor incididunt eiusmod officia cillum laboris reprehenderit laborum eiusmod officia elit.\r\n",
    "registered": "2017-09-20T05:45:51 -06:-30",
    "latitude": 2.217295,
    "longitude": 119.63918,
    "tags": [
      "esse",
      "non",
      "mollit",
      "deserunt",
      "magna",
      "eiusmod",
      "occaecat"
    ],
    "friends": [
      {
        "id": 0,
        "name": "Ina Yates"
      },
      {
        "id": 1,
        "name": "Karen Santana"
      },
      {
        "id": 2,
        "name": "Mcgee Torres"
      }
    ],
    "greeting": "Hello, Buckner Velez! You have 5 unread messages.",
    "favoriteFruit": "apple"
  },
  {
    "_id": "5d810b515e1104bc803f616a",
    "index": 49,
    "guid": "b8dcb1e2-84b0-4887-929f-d66b821c0598",
    "isActive": true,
    "balance": "$3,745.68",
    "picture": "http://placehold.it/32x32",
    "age": 24,
    "eyeColor": "brown",
    "name": "Olson Stark",
    "gender": "male",
    "company": "CORPORANA",
    "email": "olsonstark@corporana.com",
    "phone": "+1 (925) 574-2500",
    "address": "521 Tillary Street, Kieler, Northern Mariana Islands, 876",
    "about": "Ex magna cupidatat cillum consectetur consequat do. Anim aliquip do sit cillum deserunt ad exercitation officia voluptate sunt et officia excepteur adipisicing. Non et velit adipisicing ex ad cupidatat mollit ullamco id commodo ex in adipisicing. Ea ea voluptate magna Lorem aute.\r\n",
    "registered": "2016-10-28T11:29:45 -06:-30",
    "latitude": -25.473407,
    "longitude": -125.120331,
    "tags": [
      "voluptate",
      "pariatur",
      "non",
      "qui",
      "excepteur",
      "occaecat",
      "est"
    ],
    "friends": [
      {
        "id": 0,
        "name": "Obrien Lucas"
      },
      {
        "id": 1,
        "name": "Conway Huber"
      },
      {
        "id": 2,
        "name": "Roxie Bentley"
      }
    ],
    "greeting": "Hello, Olson Stark! You have 10 unread messages.",
    "favoriteFruit": "strawberry"
  },
  {
    "_id": "5d810b51ca67e4bfc4607e3b",
    "index": 50,
    "guid": "452bea10-5dbf-46ed-81ee-700177fa8815",
    "isActive": true,
    "balance": "$2,940.98",
    "picture": "http://placehold.it/32x32",
    "age": 30,
    "eyeColor": "blue",
    "name": "Maritza Tyler",
    "gender": "female",
    "company": "OPTICOM",
    "email": "maritzatyler@opticom.com",
    "phone": "+1 (950) 472-2045",
    "address": "253 Jay Street, Finzel, New Jersey, 967",
    "about": "Amet fugiat aliqua proident esse. Ad qui aliqua velit pariatur occaecat non est ex aute ex consectetur id incididunt veniam. Cupidatat enim anim ea duis mollit proident do magna ullamco. Consequat veniam dolor veniam non sint id tempor ad. Pariatur tempor sunt magna nisi. Eiusmod Lorem qui duis incididunt in exercitation consequat et nisi occaecat ipsum in exercitation do.\r\n",
    "registered": "2018-04-07T11:17:04 -06:-30",
    "latitude": -76.181506,
    "longitude": -169.792987,
    "tags": [
      "consectetur",
      "elit",
      "ex",
      "ad",
      "do",
      "exercitation",
      "laboris"
    ],
    "friends": [
      {
        "id": 0,
        "name": "Mendez Sharp"
      },
      {
        "id": 1,
        "name": "Teresa Bartlett"
      },
      {
        "id": 2,
        "name": "Francis Burris"
      }
    ],
    "greeting": "Hello, Maritza Tyler! You have 4 unread messages.",
    "favoriteFruit": "banana"
  }
]
